dns_resolver/__init__.py
dns_resolver/cli.py
dns_resolver/core.py
lightweight_dns_resolver-0.1.0.dist-info/METADATA
lightweight_dns_resolver-0.1.0.dist-info/WHEEL
lightweight_dns_resolver-0.1.0.dist-info/entry_points.txt
lightweight_dns_resolver-0.1.0.dist-info/top_level.txt
lightweight_dns_resolver-0.1.0.dist-info/RECORD
