Metadata-Version: 2.4
Name: lightweight-dns-resolver
Version: 0.1.0
Summary: A pure Python DNS resolver supporting multiple record types
Author: MissyTech
License: MIT
Classifier: License :: OSI Approved :: MIT License
Classifier: Programming Language :: Python :: 3
Dynamic: author
Dynamic: classifier
Dynamic: description
Dynamic: description-content-type
Dynamic: license
Dynamic: summary
